mcp_media_analyzer/__init__.py
mcp_media_analyzer/server.py
mcp_media_analyzer-1.0.3.dist-info/METADATA
mcp_media_analyzer-1.0.3.dist-info/WHEEL
mcp_media_analyzer-1.0.3.dist-info/entry_points.txt
mcp_media_analyzer-1.0.3.dist-info/RECORD
