Metadata-Version: 2.4
Name: mcp-media-analyzer
Version: 1.0.3
Summary: 多媒體檔案分析工具 - 支援影片、圖片和音檔的視覺分析、語音轉錄和智慧檔名建議
Project-URL: Homepage, https://github.com/hsiehchenwei/mcp-media-analyzer
Project-URL: Repository, https://github.com/hsiehchenwei/mcp-media-analyzer
Author: Chen Wei Hsieh
License: MIT
Keywords: ai,analyzer,audio,image,mcp,media,mlx,transcription,video,vision,whisper
Classifier: Development Status :: 4 - Beta
Classifier: Intended Audience :: Developers
Classifier: License :: OSI Approved :: MIT License
Classifier: Programming Language :: Python :: 3
Classifier: Programming Language :: Python :: 3.10
Classifier: Programming Language :: Python :: 3.11
Classifier: Programming Language :: Python :: 3.12
Requires-Python: >=3.10
Requires-Dist: google-genai>=1.0.0
Requires-Dist: httpx>=0.27.0
Requires-Dist: mcp>=1.0.0
Requires-Dist: mlx-whisper>=0.4.0; sys_platform == 'darwin' and platform_machine == 'arm64'
Requires-Dist: python-dotenv>=1.0.0
